pulse_linter/__init__.py
pulse_linter/dumper.py
pulse_linter/pulse_linter.py
pulse_linter/test.py
pulse_linter/Blacklist/__init__.py
pulse_linter/Blacklist/link_generator.py
pulse_linter/Blacklist/build_1/__init__.py
pulse_linter/Blacklist/build_1/base_dictionary.py
pulse_linter/Blacklist/build_1/blacklist.py
pulse_linter/Blacklist/build_1/constants.py
pulse_linter/Blacklist/build_1/cwe.py
pulse_linter/Blacklist/imports/__init__.py
pulse_linter/Blacklist/imports/base_dictionary.py
pulse_linter/Blacklist/imports/blacklist.py
pulse_linter/Blacklist/imports/cwe.py
pulse_linter/Extensions/__init__.py
pulse_linter/Extensions/common_patterns/__init__.py
pulse_linter/Extensions/common_patterns/attributes.py
pulse_linter/Extensions/common_patterns/constants.py
pulse_linter/Extensions/common_patterns/p1.py
pulse_linter/Extensions/common_patterns/p2.py
pulse_linter/Extensions/flake8_function_snake_case_checker/__init__.py
pulse_linter/Extensions/flake8_function_snake_case_checker/checker.py
pulse_linter/Extensions/package_scanner/__init__.py
pulse_linter/Extensions/package_scanner/bad_import.py
pulse_linter/Extensions/package_scanner/bad_importfrom.py
pulse_linter/Extensions/use_of_eval/__init__.py
pulse_linter/Extensions/use_of_eval/checker.py
pulse_linter/Report/__init__.py
pulse_linter/Report/report_format.py
pulse_linter/add_ons/__init__.py
pulse_linter/add_ons/eval.py
pulse_linter/add_ons/exec.py
pulse_linter/severity/__init__.py
pulse_linter/severity/calculator.py
pulse_linter/severity/code_duplications_finder.py
Pulse_Linter-0.0.24.dist-info/METADATA
Pulse_Linter-0.0.24.dist-info/WHEEL
Pulse_Linter-0.0.24.dist-info/entry_points.txt
Pulse_Linter-0.0.24.dist-info/top_level.txt
Pulse_Linter-0.0.24.dist-info/RECORD
