Metadata-Version: 2.1
Name: Pulse-Linter
Version: 0.0.24
Summary: Security Weakness Finder
Author: sooraj
Author-email: sooraj.cs22@duk.ac.in
License: Nil
Requires-Python: >3.7
Requires-Dist: flake8
Provides-Extra: dev
Requires-Dist: pytest >=7.0 ; extra == 'dev'
Requires-Dist: twine >=5.0 ; extra == 'dev'
